README.md
setup.cfg
setup.py
certbot_dns_arvancloud/__init__.py
certbot_dns_arvancloud/arvancloud_client.py
certbot_dns_arvancloud/arvancloud_client_test.py
certbot_dns_arvancloud/dns_arvancloud.py
certbot_dns_arvancloud/dns_arvancloud_test.py
certbot_dns_arvancloud/fakes.py
certbot_dns_arvancloud.egg-info/PKG-INFO
certbot_dns_arvancloud.egg-info/SOURCES.txt
certbot_dns_arvancloud.egg-info/dependency_links.txt
certbot_dns_arvancloud.egg-info/entry_points.txt
certbot_dns_arvancloud.egg-info/requires.txt
certbot_dns_arvancloud.egg-info/top_level.txt